[{"json_group_array(\n    json_object(\n        'MES', COALESCE(MES, 0),\n        'DIA', COALESCE(DIA, 0),\n        'PUBLICACION', COALESCE(PUBLICACION, ''),\n        'TITULO', COALESCE(TITULO, ''),\n        'PP', COALESCE(PP, 0),\n        'TT', COALESCE(TT, 0),\n        'DIALOGO', COALESCE(DIALOGO, ''),\n        'REVISTAS', COALESCE(REVISTAS, ''),\n        'COLECCIONES', COALESCE(COLECCIONES, '')\n    )\n)":"[{\"MES\":0,\"DIA\":0,\"PUBLICACION\":\"ZZ Nº 79 LA JUNGLA MISTERIOSA\",\"TITULO\":\"LEONCIO, EL LEÓN\",\"PP\":4,\"TT\":4,\"DIALOGO\":\"LES ACOMPAÑARÉ A SU BUNGALOW\",\"REVISTAS\":\"ZZ Nº 79 LA JUNGLA MISTERIOSA\",\"COLECCIONES\":\"MUNDO2005-20, OP313, OG48\"},{\"MES\":0,\"DIA\":0,\"PUBLICACION\":\"ZZ Nº 84 EXTRA FLORECILLAS\",\"TITULO\":\"LA PRIMAVERA LOCA\",\"PP\":5,\"TT\":4,\"DIALOGO\":\" \",\"REVISTAS\":\"ZZ Nº 84 EXTRA FLORECILLAS\",\"COLECCIONES\":\"\"},{\"MES\":0,\"DIA\":0,\"PUBLICACION\":\"ZZ Nº 92 EXTRA ¡TODOS AL CAMPO!\",\"TITULO\":\"¡QUÉ GRANDE ES EL CAMPO!\",\"PP\":4,\"TT\":4,\"DIALOGO\":\" \",\"REVISTAS\":\"ZZ Nº 92 EXTRA ¡TODOS AL CAMPO!\",\"COLECCIONES\":\"OP388, OG64, DIARIO3, MUNDO2005-02\"},{\"MES\":1,\"DIA\":0,\"PUBLICACION\":\"ZZ605\",\"TITULO\":\"MÁS CONSEJOS DE PAPÁ\",\"PP\":4,\"TT\":4,\"DIALOGO\":\"Y ENTONCES...BLA..BLA\",\"REVISTAS\":\"ZZ605\",\"COLECCIONES\":\"MUNDO2005-17, SALVAT58, OP313, OG50\"},{\"MES\":1,\"DIA\":0,\"PUBLICACION\":\"ZZ606\",\"TITULO\":\"HOGAR, DULCE HOGAR (DULCE HOGAR) (A)\",\"PP\":4,\"TT\":4,\"DIALOGO\":\"EN CAMBIO, EN VERANO SE LLEVAN\",\"REVISTAS\":\"ZZ606\",\"COLECCIONES\":\"MUNDO2005-20, SALVAT58, OP313, OG47\"},{\"MES\":1,\"DIA\":0,\"PUBLICACION\":\"ZZ607\",\"TITULO\":\"VANIDAD Y PETULANCIA\",\"PP\":4,\"TT\":4,\"DIALOGO\":\"NO PRESUMÁIS DEMASIADO\",\"REVISTAS\":\"ZZ607\",\"COLECCIONES\":\"MUNDO2005-20, OP313, OG48\"},{\"MES\":0,\"DIA\":0,\"PUBLICACION\":\"ZZ608\",\"TITULO\":\"VENTAJAS DE LA SUCIEDAD\",\"PP\":4,\"TT\":4,\"DIALOGO\":\"¿NO OS MANDÉ QUE LIMPIÁRAIS EL CRISTAL\",\"REVISTAS\":\"ZZ608\",\"COLECCIONES\":\"MUNDO2005-20, SALVAT58, OP313, OG48\"},{\"MES\":0,\"DIA\":0,\"PUBLICACION\":\"ZZ612\",\"TITULO\":\"MISTERIOS DE LA GENÉTICA\",\"PP\":4,\"TT\":4,\"DIALOGO\":\"VE Y VE, PERO QUE ELLOS NO\",\"REVISTAS\":\"ZZ612\",\"COLECCIONES\":\"MUNDO2005-17, SALVAT58, OP313, OG50\"},{\"MES\":3,\"DIA\":0,\"PUBLICACION\":\"ZZ613\",\"TITULO\":\"INOCENTES ADELANTADOS\",\"PP\":4,\"TT\":4,\"DIALOGO\":\"ZAPE, EN LA ORACIÓN\",\"REVISTAS\":\"ZZ613\",\"COLECCIONES\":\"MUNDO2005-17, SALVAT58, OP313, OG50\"},{\"MES\":3,\"DIA\":0,\"PUBLICACION\":\"ZZ615\",\"TITULO\":\"UN SELLO INÚTIL\",\"PP\":4,\"TT\":4,\"DIALOGO\":\"¿Y LOS NENES? ¿QUÉ EXCUSA LES DAREMOS?\",\"REVISTAS\":\"ZZ615\",\"COLECCIONES\":\"SALVAT58\"},{\"MES\":4,\"DIA\":0,\"PUBLICACION\":\"ZZ617\",\"TITULO\":\"BIGOTES Y BARBAS\",\"PP\":4,\"TT\":4,\"DIALOGO\":\"CON LO BIEN QUE ME SENTARIA UN HELADO DE FRESA\",\"REVISTAS\":\"ZZ617\",\"COLECCIONES\":\"SALVAT58\"},{\"MES\":4,\"DIA\":0,\"PUBLICACION\":\"ZZ619\",\"TITULO\":\"ADIOS, PATILLAS\",\"PP\":4,\"TT\":4,\"DIALOGO\":\"¡MAGNÍFICO!\",\"REVISTAS\":\"ZZ619\",\"COLECCIONES\":\"SALVAT58\"},{\"MES\":0,\"DIA\":0,\"PUBLICACION\":\"ZZ622\",\"TITULO\":\"DUDA CONTAGIOSA\",\"PP\":4,\"TT\":4,\"DIALOGO\":\" \",\"REVISTAS\":\"ZZ622\",\"COLECCIONES\":\"OP341, OG58, MUNDO2005-17, SALVAT58\"},{\"MES\":0,\"DIA\":0,\"PUBLICACION\":\"ZZ623\",\"TITULO\":\"ESOS ABUELOS...\",\"PP\":4,\"TT\":4,\"DIALOGO\":\"LA ABUELITA OS INVITA A COMER\",\"REVISTAS\":\"ZZ623\",\"COLECCIONES\":\"MUNDO2005-14, SALVAT58, OP339, OG58\"},{\"MES\":0,\"DIA\":0,\"PUBLICACION\":\"ZZ625\",\"TITULO\":\"ESA MEMORIA...\",\"PP\":4,\"TT\":4,\"DIALOGO\":\"PUES ES VERDAD\",\"REVISTAS\":\"ZZ625\",\"COLECCIONES\":\"MUNDO2005-17, SALVAT58, OP339, OG58\"},{\"MES\":0,\"DIA\":0,\"PUBLICACION\":\"ZZ626\",\"TITULO\":\"EL BERENJENO\",\"PP\":4,\"TT\":4,\"DIALOGO\":\"¿POR QUÉ NO?\",\"REVISTAS\":\"ZZ626\",\"COLECCIONES\":\"MUNDO2005-17, SALVAT59, OP339, OG58\"},{\"MES\":0,\"DIA\":0,\"PUBLICACION\":\"ZZ627\",\"TITULO\":\"UN DOMINGO NORMAL\",\"PP\":4,\"TT\":4,\"DIALOGO\":\"Y LLEGA EL DOMINGO\",\"REVISTAS\":\"ZZ627\",\"COLECCIONES\":\"SALVAT59, OP339, OG58\"},{\"MES\":9,\"DIA\":0,\"PUBLICACION\":\"ZZ637\",\"TITULO\":\"SURFING CASERO\",\"PP\":4,\"TT\":4,\"DIALOGO\":\"OS LA DEJO SOBRE ESTE TABURETE\",\"REVISTAS\":\"ZZ637\",\"COLECCIONES\":\"MUNDO2005-17, SALVAT59, OP339, OG58\"},{\"MES\":10,\"DIA\":0,\"PUBLICACION\":\"ZZ638\",\"TITULO\":\"MULTAS A GOGÓ\",\"PP\":4,\"TT\":4,\"DIALOGO\":\" \",\"REVISTAS\":\"ZZ638\",\"COLECCIONES\":\"OP346, OG56, MUNDO2005-14, SALVAT59\"},{\"MES\":0,\"DIA\":0,\"PUBLICACION\":\"ZZ645\",\"TITULO\":\"¡PIO, PIOO, PIOOO!\",\"PP\":4,\"TT\":4,\"DIALOGO\":\" \",\"REVISTAS\":\"ZZ645\",\"COLECCIONES\":\"SALVAT59\"},{\"MES\":0,\"DIA\":0,\"PUBLICACION\":\"ZZ646\",\"TITULO\":\"LA ASIGNACIÓN\",\"PP\":4,\"TT\":4,\"DIALOGO\":\" \",\"REVISTAS\":\"ZZ646\",\"COLECCIONES\":\"SALVAT59\"},{\"MES\":12,\"DIA\":0,\"PUBLICACION\":\"ZZ647\",\"TITULO\":\"LA CARRERA (B)\",\"PP\":4,\"TT\":4,\"DIALOGO\":\"MIRA, TOBY, POR ALLÍ VA TOBY\",\"REVISTAS\":\"ZZ647, ZXB34\",\"COLECCIONES\":\"SALVAT59, OP324, OG51\"},{\"MES\":12,\"DIA\":0,\"PUBLICACION\":\"ZZ648\",\"TITULO\":\"CHULETAS\",\"PP\":4,\"TT\":4,\"DIALOGO\":\" \",\"REVISTAS\":\"ZZ648\",\"COLECCIONES\":\"SALVAT59\"},{\"MES\":12,\"DIA\":0,\"PUBLICACION\":\"ZZ649\",\"TITULO\":\"BARBAS\",\"PP\":4,\"TT\":4,\"DIALOGO\":\"¡CUÁNTO TIEMPO SIN VERTE...!\",\"REVISTAS\":\"ZZ649\",\"COLECCIONES\":\"SALVAT59\"},{\"MES\":1,\"DIA\":7,\"PUBLICACION\":\"ZE143\",\"TITULO\":\"LA OLA DE FRÍO (B)\",\"PP\":4,\"TT\":4,\"DIALOGO\":\"BUENOS DÍAS, DON MINERVO\",\"REVISTAS\":\"ZE143, ZXB35\",\"COLECCIONES\":\"SALVAT57, OP303\"},{\"MES\":1,\"DIA\":21,\"PUBLICACION\":\"ZE144\",\"TITULO\":\"BRUJERÍAS\",\"PP\":4,\"TT\":4,\"DIALOGO\":\"A SU DEBIDO TIEMPO\",\"REVISTAS\":\"ZE144\",\"COLECCIONES\":\"MUNDO2005-20, SALVAT57, OP313, OG48\"},{\"MES\":2,\"DIA\":4,\"PUBLICACION\":\"ZE145\",\"TITULO\":\"UNA FINAL DE LIGA\",\"PP\":5,\"TT\":4,\"DIALOGO\":\"PUES EL PARADÓN DEL\",\"REVISTAS\":\"ZE145\",\"COLECCIONES\":\"MUNDO2005-14, SALVAT57, OP337, OG56\"},{\"MES\":2,\"DIA\":18,\"PUBLICACION\":\"ZE146\",\"TITULO\":\"EL EDREDÓN\",\"PP\":5,\"TT\":4,\"DIALOGO\":\"CUANDO OS CONOZCA\",\"REVISTAS\":\"ZE146\",\"COLECCIONES\":\"SALVAT57, OP313, OG64\"},{\"MES\":3,\"DIA\":4,\"PUBLICACION\":\"ZE147\",\"TITULO\":\"EL REFRÁN EQUIVOCADO\",\"PP\":5,\"TT\":4,\"DIALOGO\":\"Y COMO EL REFRAN DICE\",\"REVISTAS\":\"ZE147\",\"COLECCIONES\":\"SALVAT57\"},{\"MES\":3,\"DIA\":18,\"PUBLICACION\":\"ZE148\",\"TITULO\":\"EXPLORADORES CASEROS\",\"PP\":4,\"TT\":4,\"DIALOGO\":\"TODO LO EXPLORABLE\",\"REVISTAS\":\"ZE148\",\"COLECCIONES\":\"SALVAT57\"},{\"MES\":4,\"DIA\":1,\"PUBLICACION\":\"ZE149\",\"TITULO\":\"FANTASMAS VETERANOS\",\"PP\":5,\"TT\":4,\"DIALOGO\":\"NO QUERRA. YA SABES QUE EL TERROR\",\"REVISTAS\":\"ZE149\",\"COLECCIONES\":\"SALVAT57\"},{\"MES\":4,\"DIA\":15,\"PUBLICACION\":\"ZE150\",\"TITULO\":\"UN ARMARIO PRIMAVERAL\",\"PP\":4,\"TT\":4,\"DIALOGO\":\"¡VEO PUERTA! FIJATE EN MI DISPARO\",\"REVISTAS\":\"ZE150\",\"COLECCIONES\":\"MUNDO2005-14, SALVAT57, OP334, OG61\"},{\"MES\":5,\"DIA\":6,\"PUBLICACION\":\"ZE151\",\"TITULO\":\"¡MATRÍCULA DE HONOR!\",\"PP\":4,\"TT\":4,\"DIALOGO\":\"SÓLO HE PUESTO TRES PREGUNTAS POR RESPETO\",\"REVISTAS\":\"ZE151\",\"COLECCIONES\":\"MUNDO2005-14, SALVAT59, OP334, OG61\"},{\"MES\":5,\"DIA\":20,\"PUBLICACION\":\"ZE152\",\"TITULO\":\"¿CHUPI O CUCHI?\",\"PP\":4,\"TT\":4,\"DIALOGO\":\"YA ESTAMOS EN EL PASEO\",\"REVISTAS\":\"ZE152\",\"COLECCIONES\":\"MUNDO2005-14, OP334, OG61\"},{\"MES\":6,\"DIA\":3,\"PUBLICACION\":\"ZE153\",\"TITULO\":\"TRANSMUTACIÓN\",\"PP\":4,\"TT\":4,\"DIALOGO\":\"¡MUÉSTRATE, TRASGO, ESPÍRITU\",\"REVISTAS\":\"ZE153\",\"COLECCIONES\":\"MUNDO2005-14, OP334, OG61\"},{\"MES\":6,\"DIA\":17,\"PUBLICACION\":\"ZE154\",\"TITULO\":\"VÍDEO-JUGANDO\",\"PP\":4,\"TT\":4,\"DIALOGO\":\" \",\"REVISTAS\":\"ZE154\",\"COLECCIONES\":\"OP317, OG49, MUNDO2005-17, SALVAT57\"},{\"MES\":7,\"DIA\":1,\"PUBLICACION\":\"ZE155\",\"TITULO\":\"BREAK-DANCE ONEROSO\",\"PP\":4,\"TT\":4,\"DIALOGO\":\" \",\"REVISTAS\":\"ZE155\",\"COLECCIONES\":\"OP317, OG49, MUNDO2005-17, SALVAT57\"},{\"MES\":7,\"DIA\":15,\"PUBLICACION\":\"ZE156\",\"TITULO\":\"EL REVEILLÓN\",\"PP\":4,\"TT\":4,\"DIALOGO\":\" \",\"REVISTAS\":\"ZE156, ZXB47\",\"COLECCIONES\":\"OP344, SALVAT59\"},{\"MES\":8,\"DIA\":5,\"PUBLICACION\":\"ZE157\",\"TITULO\":\"REYES ACCIDENTADOS\",\"PP\":4,\"TT\":4,\"DIALOGO\":\" \",\"REVISTAS\":\"ZE157, ZXB36\",\"COLECCIONES\":\"OP324, OG51, SALVAT61\"},{\"MES\":8,\"DIA\":19,\"PUBLICACION\":\"ZE158\",\"TITULO\":\"UTILIDADES DEL YO-YO\",\"PP\":4,\"TT\":4,\"DIALOGO\":\" \",\"REVISTAS\":\"ZE158\",\"COLECCIONES\":\"OP317, OG49, MUNDO2005-17, SALVAT61\"},{\"MES\":9,\"DIA\":2,\"PUBLICACION\":\"ZE159\",\"TITULO\":\"LOS INNOVADORES\",\"PP\":4,\"TT\":4,\"DIALOGO\":\" \",\"REVISTAS\":\"ZE159\",\"COLECCIONES\":\"OP317, OG49, MUNDO2005-17, SALVAT61\"},{\"MES\":9,\"DIA\":16,\"PUBLICACION\":\"ZE160\",\"TITULO\":\"COMO PERRO Y GATO\",\"PP\":4,\"TT\":4,\"DIALOGO\":\"ADEMÁS LA JUNTA DE LA FACULTAD DE FILATELIA\",\"REVISTAS\":\"ZE160, ZXB37\",\"COLECCIONES\":\"OP324, OG51\"},{\"MES\":10,\"DIA\":7,\"PUBLICACION\":\"ZE161\",\"TITULO\":\"¡VAYA PASTEL!\",\"PP\":4,\"TT\":4,\"DIALOGO\":\" \",\"REVISTAS\":\"ZE161\",\"COLECCIONES\":\"OP305, OG47, SALVAT61\"},{\"MES\":10,\"DIA\":21,\"PUBLICACION\":\"ZE162\",\"TITULO\":\"HORRORES HORROROSOS\",\"PP\":4,\"TT\":4,\"DIALOGO\":\" \",\"REVISTAS\":\"ZE162\",\"COLECCIONES\":\"OP317, OG49, SALVAT61\"},{\"MES\":11,\"DIA\":4,\"PUBLICACION\":\"ZE163\",\"TITULO\":\"EL BUEN GNOMO\",\"PP\":4,\"TT\":4,\"DIALOGO\":\" \",\"REVISTAS\":\"ZE163, SZB136\",\"COLECCIONES\":\"OP324, OG51, SALVAT61\"},{\"MES\":11,\"DIA\":18,\"PUBLICACION\":\"ZE164\",\"TITULO\":\"CANTAUTORES\",\"PP\":4,\"TT\":4,\"DIALOGO\":\" \",\"REVISTAS\":\"ZE164, SZB136\",\"COLECCIONES\":\"OP324, OG51, SALVAT61\"},{\"MES\":12,\"DIA\":2,\"PUBLICACION\":\"ZE165\",\"TITULO\":\"ATRACCIÓN TERRÁQUEA\",\"PP\":8,\"TT\":4,\"DIALOGO\":\" \",\"REVISTAS\":\"ZE165, ZXB34\",\"COLECCIONES\":\"OP324, OG51\"},{\"MES\":12,\"DIA\":16,\"PUBLICACION\":\"ZE166\",\"TITULO\":\"PRIMAVERA RETRASADA\",\"PP\":8,\"TT\":4,\"DIALOGO\":\" \",\"REVISTAS\":\"ZE166, ZXB39\",\"COLECCIONES\":\"OP324, OG51\"},{\"MES\":12,\"DIA\":30,\"PUBLICACION\":\"ZE167\",\"TITULO\":\"¡CARAY CON EL KARATE!\",\"PP\":8,\"TT\":4,\"DIALOGO\":\" \",\"REVISTAS\":\"ZE167\",\"COLECCIONES\":\"OP368, OG58, MUNDO2005-14\"}]"}]
